LICENSE
MANIFEST.in
README.rst
inbox.py
setup.py
inbox.py.egg-info/PKG-INFO
inbox.py.egg-info/SOURCES.txt
inbox.py.egg-info/dependency_links.txt
inbox.py.egg-info/requires.txt
inbox.py.egg-info/top_level.txt