Metadata-Version: 1.1
Name: inbox.py
Version: 0.0.6
Summary: SMTP for Humans.
Home-page: https://github.com/kennethreitz/inbox.py
Author: Kenneth Reitz
Author-email: me@kennethreitz.com
License: BSD
Platform: UNKNOWN
Classifier: Intended Audience :: Developers
Classifier: Natural Language :: English
Classifier: License :: OSI Approved :: BSD License
Classifier: Programming Language :: Python
Classifier: Programming Language :: Python :: 2.6
Classifier: Programming Language :: Python :: 2.7
